Metadata-Version: 1.0
Name: onigiri
Version: 0.0.3
Summary: Unofficial RIT Translate
Home-page: UNKNOWN
Author: UNKNOWN
Author-email: UNKNOWN
License: Apache v2.0
Platform: UNKNOWN
